{"numero":"BR 11 2024 000663-8","pedidoInternacional":{"numeroPCT":"PCT RU2022/050173","dataPCT":"30/05/2022"},"publicacaoInternacional":{"numeroOMPI":"WO 2023/287324","dataOMPI":"19/01/2023"},"IPC":["C12N 15/117","C12N 15/50","A61P 31/14","A61P 31/16","C07K 14/165","A61K 39/215","A61P 37/04"],"prioridadesUnionistas":[{"siglaPais":"RU","numeroPrioridade":"2021121139","dataPrioridade":"16/07/2021"}],"despachos":[{"codigo":"1.1","titulo":"Pedido Internacional PCT Publicado. Petição de Requerimento de Entrada na Fase Nacional Recebida","rpi":"2768"}]}