{"numero":"BR 11 2023 027657-8","pedidoInternacional":{"numeroPCT":"PCT FR2022/050952","dataPCT":"19/05/2022"},"publicacaoInternacional":{"numeroOMPI":"WO 2023/281171","dataOMPI":"12/01/2023"},"IPC":["B29C 33/02","B29C 33/38","B29C 33/40","B29C 70/88","B29C 70/46","B29L 31/08","B29L 31/30"],"prioridadesUnionistas":[{"siglaPais":"FR","numeroPrioridade":"FR2107440","dataPrioridade":"08/07/2021"}],"despachos":[{"codigo":"1.1","titulo":"Pedido Internacional PCT Publicado. Petição de Requerimento de Entrada na Fase Nacional Recebida","rpi":"2766"}]}