{"numero":"BR 11 2024 000998-0","pedidoInternacional":{"numeroPCT":"PCT CN2022/087009","dataPCT":"15/04/2022"},"publicacaoInternacional":{"numeroOMPI":"WO 2023/029494","dataOMPI":"09/03/2023"},"IPC":["G06F 30/27","G06K 9/62","G06N 3/04","G06N 20/00","G05D 23/20"],"prioridadesUnionistas":[{"siglaPais":"CN","numeroPrioridade":"202111004178.X","dataPrioridade":"30/08/2021"}],"despachos":[{"codigo":"1.1","titulo":"Pedido Internacional PCT Publicado. Petição de Requerimento de Entrada na Fase Nacional Recebida","rpi":"2769"}]}