{"numero":"BR 11 2024 003220-5","pedidoInternacional":{"numeroPCT":"PCT RU2022/050257","dataPCT":"21/08/2022"},"publicacaoInternacional":{"numeroOMPI":"WO 2023/022633","dataOMPI":"23/02/2023"},"IPC":["C07K 14/075","C07K 14/005","C12N 15/861","C12N 7/01","C12N 15/09","A61K 48/00"],"prioridadesUnionistas":[{"siglaPais":"RU","numeroPrioridade":"2021124727","dataPrioridade":"20/08/2021"}],"despachos":[{"codigo":"1.1","titulo":"Pedido Internacional PCT Publicado. Petição de Requerimento de Entrada na Fase Nacional Recebida","rpi":"2773"}]}